{
  "title": "BSEB कक्षा 10 - जीवविज्ञान",
  "subtitle": "अध्याय 7 - आनुवंशिकता तथा जैव विकास",
  "description": "भारती भवन जीवविज्ञान अध्याय 7 (आनुवंशिकता तथा जैव विकास) पर आधारित 100 अति-महत्वपूर्ण वस्तुनिष्ठ प्रश्नों का विस्तृत ऑनलाइन टेस्ट सेट।",
  "questions": [
    {
      "q": "आनुवंशिकी का पिता निम्नलिखित में से किसे कहा जाता है?",
      "o": ["ग्रैगर जॉन मेंडल", "चार्लस डार्विन", "लैमार्क", "अरस्तू"],
      "a": 0
    },
    {
      "q": "मेंडल ने अपने आनुवंशिकी के प्रयोग किस पौधे पर किए थे?",
      "o": ["चना पर", "साधारण मटर पर", "गुलाब पर", "गेहूँ पर"],
      "a": 1
    },
    {
      "q": "मनुष्य की कोशिका में कुल कितने गुणसूत्र पाए जाते हैं?",
      "o": ["23 गुणसूत्र", "44 गुणसूत्र", "46 गुणसूत्र", "48 गुणसूत्र"],
      "a": 2
    },
    {
      "q": "मानव में लिंग गुणसूत्रों की संख्या कितनी होती है?",
      "o": ["44 गुणसूत्र", "23 गुणसूत्र", "46 गुणसूत्र", "2 गुणसूत्र"],
      "a": 3
    },
    {
      "q": "पुरुषों में पाया जाने वाला लिंग गुणसूत्र कौन सा है?",
      "o": ["XY गुणसूत्र", "XX गुणसूत्र", "YY गुणसूत्र", "XO गुणसूत्र"],
      "a": 0
    },
    {
      "q": "स्त्रियों में पाया जाने वाला लिंग गुणसूत्र कौन सा है?",
      "o": ["XY गुणसूत्र", "XX गुणसूत्र", "YY गुणसूत्र", "XO गुणसूत्र"],
      "a": 1
    },
    {
      "q": "बच्चे के लिंग का निर्धारण मुख्य रूप से किसके गुणसूत्र पर निर्भर करता है?",
      "o": ["माता के", "पिता के", "गाँव के", "पर्यावरण के"],
      "a": 1
    },
    {
      "q": "द ओरिजिन ऑफ स्पीशीज नामक पुस्तक के लेखक कौन हैं?",
      "o": ["मेंडल", "लैमार्क", "अरस्तू", "चार्ल्स डार्विन"],
      "a": 3
    },
    {
      "q": "जीन शब्द की स्थापना सबसे पहले किसने की थी?",
      "o": ["जोहान्सन ने", "मेंडल ने", "डार्विन ने", "मोगन ने"],
      "a": 0
    },
    {
      "q": "गुणसूत्र मुख्य रूप से किसके बने होते हैं?",
      "o": ["केवल वसा के", "डीएनए तथा प्रोटीन के", "केवल कार्बोहाइड्रेट के", "केवल आरएनए के"],
      "a": 1
    },
    {
      "q": "जीन कहाँ पाए जाते हैं?",
      "o": ["कोशिका द्रव में", "रसधानी में", "गुणसूत्रों पर", "गोल्जीकाय में"],
      "a": 2
    },
    {
      "q": "जैव विकास का प्राकृतिक चयन का सिद्धांत किसने दिया था?",
      "o": ["मेंडल ने", "लैमार्क ने", "अरस्तू ने", "डार्विन ने"],
      "a": 3
    },
    {
      "q": "उपार्जित लक्षणों की वंशागति का सिद्धांत किसने प्रस्तुत किया?",
      "o": ["लैमार्क ने", "डार्विन ने", "मेंडल ने", "वीजमैन ने"],
      "a": 0
    },
    {
      "q": "समजात अंगों का उदाहरण निम्नलिखित में से कौन सा है?",
      "o": ["हमारा हाथ और कुत्ते के अग्रपाद", "हमारा हाथ और हाथी का दाँत", "आलू और घास के उपरी भूस्तारी", "इनमें से सभी"],
      "a": 3
    },
    {
      "q": "असमजात (समवृत्ति) अंगों का उदाहरण कौन सा है?",
      "o": ["मानव हाथ और बिल्ली के पंजे", "पक्षियों के पंख और कीटों के पंख", "हाथी के दाँत और मनुष्य के दाँत", "घोड़े के पैर और मानव हाथ"],
      "a": 1
    },
    {
      "q": "मानव शरीर में पाए जाने वाले अवशेषी अंग का उदाहरण कौन सा है?",
      "o": ["हृदय", "यकृत", "अपेंडिक्स", "फेफड़ा"],
      "a": 2
    },
    {
      "q": "कीटों के पंख और चमगादड़ के पंख किस प्रकार के अंग हैं?",
      "o": ["समजात अंग", "अवशेषी अंग", "निष्क्रिय अंग", "समवृत्ति अंग"],
      "a": 3
    },
    {
      "q": "मेंडल के एकसंकर क्रॉस का दर्श प्रारूप (फेनोटाइपिक) अनुपात क्या था?",
      "o": ["3:1 का अनुपात", "1:2:1 का अनुपात", "9:3:3:1 का अनुपात", "2:1 का अनुपात"],
      "a": 0
    },
    {
      "q": "मेंडल के एकसंकर क्रॉस का जीनोटाइपिक अनुपात क्या था?",
      "o": ["3:1 का अनुपात", "1:2:1 का अनुपात", "9:3:3:1 का अनुपात", "1:1 का अनुपात"],
      "a": 1
    },
    {
      "q": "द्विसंकर संकरण में फेनोटाइपिक अनुपात क्या प्राप्त होता है?",
      "o": ["3:1 का अनुपात", "1:2:1 का अनुपात", "9:3:3:1 का अनुपात", "1:3 का अनुपात"],
      "a": 2
    },
    {
      "q": "जीवों की शारीरिक संरचना में समय के साथ आए परिवर्तनों को क्या कहते हैं?",
      "o": ["आनुवंशिकता", "उत्परिवर्तन", "अनुकूलन", "जैव विकास"],
      "a": 3
    },
    {
      "q": "डीएनए का पूर्ण रूप निम्नलिखित में से क्या है?",
      "o": ["डीऑक्सीराइबो न्यूक्लिक अम्ल", "डायरेक्ट न्यूक्लिक एसिड", "डीऑक्सी न्यूक्लिक एसिड", "डिजिटल न्यूक्लिक अम्ल"],
      "a": 0
    },
    {
      "q": "अनुवंशिक गुणों का संदेश कहाँ उपस्थित होता है?",
      "o": ["कोशिका द्रव में", "डीएनए अणुओं में", "रसधानी में", "माइटोकॉन्ड्रिया में"],
      "a": 1
    },
    {
      "q": "मेंडल ने अपने प्रयोग में मटर के पौधे के कितने लक्षणों का अध्ययन किया?",
      "o": ["5 लक्षणों का", "6 लक्षणों का", "7 लक्षणों का", "8 लक्षणों का"],
      "a": 2
    },
    {
      "q": "प्रथम संतति पीढ़ी को किस संकेत से दर्शाया जाता है?",
      "o": ["P पीढ़ी", "F2 पीढ़ी", "F3 पीढ़ी", "F1 पीढ़ी"],
      "a": 3
    },
    {
      "q": "द्वितीयांश संतति पीढ़ी को किस संकेत से व्यक्त किया जाता है?",
      "o": ["F2 पीढ़ी", "F1 पीढ़ी", "P पीढ़ी", "X पीढ़ी"],
      "a": 0
    },
    {
      "q": "शुद्ध लंबे मटर के पौधे का आनुवंशिक प्रारूप क्या होता है?",
      "o": ["Tt प्रारूप", "TT प्रारूप", "tt प्रारूप", "tT प्रारूप"],
      "a": 1
    },
    {
      "q": "शुद्ध बौने मटर के पौधे का आनुवंशिक प्रारूप क्या होता है?",
      "o": ["TT प्रारूप", "Tt प्रारूप", "tt प्रारूप", "tT प्रारूप"],
      "a": 2
    },
    {
      "q": "संकर लंबे मटर के पौधे को किस संकेत द्वारा दर्शाया जाता है?",
      "o": ["TT संकेत", "tt संकेत", "tT संकेत", "Tt संकेत"],
      "a": 3
    },
    {
      "q": "आनुवंशिक विभिन्नता का मुख्य स्रोत क्या माना जाता है?",
      "o": ["उत्परिवर्तन एवं पुनर्योजन", "पोषण", "श्वसन", "उत्सर्जन"],
      "a": 0
    },
    {
      "q": "समान संरचना लेकिन भिन्न कार्य करने वाले अंगों को क्या कहते हैं?",
      "o": ["समवृत्ति अंग", "समजात अंग", "अवशेषी अंग", "कृत्रिम अंग"],
      "a": 1
    },
    {
      "q": "भिन्न संरचना लेकिन एक समान कार्य करने वाले अंगों को क्या कहते हैं?",
      "o": ["समजात अंग", "अवशेषी अंग", "समवृत्ति अंग", "निषेचित अंग"],
      "a": 2
    },
    {
      "q": "शरीर में बिना किसी उपयोग के पाए जाने वाले अंगों को क्या कहते हैं?",
      "o": ["समजात अंग", "समवृत्ति अंग", "सक्रिय अंग", "अवशेषी अंग"],
      "a": 3
    },
    {
      "q": "प्राचीन जीवों के अवशेषों को क्या कहा जाता है?",
      "o": ["जीवाश्म", "कंकाल", "चट्टान", "मिट्टी"],
      "a": 0
    },
    {
      "q": "जीवाश्मों की आयु का निर्धारण किस विधि द्वारा किया जाता है?",
      "o": ["जल विश्लेषण", "रेडियोकार्बन काल-निर्धारण", "थर्मामीटर विधि", "आनुवंशिक परीक्षण"],
      "a": 1
    },
    {
      "q": "मनुष्य का सबसे नजदीकी सम्बंधी कौन सा जीव माना जाता है?",
      "o": ["लंगूर", "बंदर", "चिंपैंजी", "गोरिल्ला"],
      "a": 2
    },
    {
      "q": "आधुनिक मानव का वैज्ञानिक नाम निम्नलिखित में से क्या है?",
      "o": ["होमो इरेक्टस", "रामापिथेकस", "ऑस्ट्रैलोपिथेकस", "होमो सेपियंस"],
      "a": 3
    },
    {
      "q": "मानव प्रजाति का उद्भव मुख्य रूप से किस महाद्वीप में हुआ था?",
      "o": ["अफ्रीका महाद्वीप में", "एशिया महाद्वीप में", "यूरोप महाद्वीप में", "अमेरिका महाद्वीप में"],
      "a": 0
    },
    {
      "q": "वह प्रक्रिया जिसके द्वारा नए जीवों की प्रजाति बनती है क्या कहलाती है?",
      "o": ["विभिन्नता", "प्रजातीकरण (जाति-उद्भव)", "अनुकूलन", "आनुवंशिकता"],
      "a": 1
    },
    {
      "q": "एक ही माता-पिता की संतानों में पाई जाने वाली असमानता को क्या कहते हैं?",
      "o": ["वंशागति", "समानता", "विभिन्नता", "आनुवंशिकता"],
      "a": 2
    },
    {
      "q": "काहिक विभिन्नताएँ किस प्रकार की कोशिकाओं में उत्पन्न होती हैं?",
      "o": ["जनन कोशिकाओं में", "युग्मक कोशिकाओं में", "अंड कोशिकाओं में", "कायिक कोशिकाओं में"],
      "a": 3
    },
    {
      "q": "जनन कोशिकीय विभिन्नताएँ कैसी होती हैं?",
      "o": ["वंशागत होती हैं", "अवंशागत होती हैं", "अस्थायी होती हैं", "नष्ट हो जाती हैं"],
      "a": 0
    },
    {
      "q": "मेंडल ने अपने प्रयोग के लिए मटर के पौधे का चयन क्यों किया?",
      "o": ["यह महँगा था", "यह आसानी से उपलब्ध था", "इसमें विविधताएँ नहीं थीं", "यह एकवर्षीय था"],
      "a": 1
    },
    {
      "q": "प्रभावी लक्षण किस पीढ़ी में स्पष्ट रूप से दिखाई देता है?",
      "o": ["P पीढ़ी में", "F2 पीढ़ी में", "F1 पीढ़ी में", "F3 पीढ़ी में"],
      "a": 2
    },
    {
      "q": "अप्रभावी लक्षण F1 पीढ़ी में कैसा रहता है?",
      "o": ["प्रकट होता है", "नष्ट हो जाता है", "बदल जाता है", "छिपा रहता है"],
      "a": 3
    },
    {
      "q": "लिंग का निर्धारण करने वाले गुणसूत्रों को क्या कहते हैं?",
      "o": ["लिंग गुणसूत्र", "ऑटोसोम", "कायिक गुणसूत्र", "विषम गुणसूत्र"],
      "a": 0
    },
    {
      "q": "दैहिक लक्षणों का निर्धारण करने वाले गुणसूत्रों को क्या कहते हैं?",
      "o": ["लिंग गुणसूत्र", "ऑटोसोम", "युग्मक", "जीन"],
      "a": 1
    },
    {
      "q": "मनुष्य की जनन कोशिकाओं में गुणसूत्रों की संख्या कितनी होती है?",
      "o": ["46 गुणसूत्र", "22 गुणसूत्र", "23 गुणसूत्र", "44 गुणसूत्र"],
      "a": 2
    },
    {
      "q": "किसी जीव की जीनी संरचना को क्या कहा जाता है?",
      "o": ["फेनोटाइप", "लक्षण प्रारूप", "अनुपात", "जीनोटाइप"],
      "a": 3
    },
    {
      "q": "जीवों के बाह्य लक्षण और रूप को क्या कहते हैं?",
      "o": ["फेनोटाइप", "जीनोटाइप", "गुणसूत्र", "विभिन्नता"],
      "a": 0
    },
    {
      "q": "अनुवंशिकता के नियमों का प्रतिपादन किसने किया था?",
      "o": ["डार्विन ने", "ग्रैगर जॉन मेंडल ने", "लैमार्क ने", "वाटसन ने"],
      "a": 1
    },
    {
      "q": "मेंडल का प्रथम नियम निम्नलिखित में से कौन सा है?",
      "o": ["स्वतंत्र अपव्यूहन का नियम", "संरक्षण का नियम", "प्रभाविता का नियम", "उत्परिवर्तन का नियम"],
      "a": 2
    },
    {
      "q": "मेंडल का द्वितीय नियम किस नाम से जाना जाता है?",
      "o": ["प्रभाविता का नियम", "उत्परिवर्तन का नियम", "अविभाज्यता का नियम", "पृथक्करण का नियम"],
      "a": 3
    },
    {
      "q": "पृथक्करण के नियम को और किस नाम से जाना जाता है?",
      "o": ["युग्मकों की शुद्धता का नियम", "प्रभाविता का नियम", "विकास का नियम", "पर्यावरण का नियम"],
      "a": 0
    },
    {
      "q": "मेंडल का तृतीय नियम कौन सा कहलाता है?",
      "o": ["प्रभाविता का नियम", "स्वतंत्र अपव्यूहन का नियम", "पृथक्करण का नियम", "उत्परिवर्तन का नियम"],
      "a": 1
    },
    {
      "q": "घोड़े का अति प्राचीन पूर्वज किसे माना जाता है?",
      "o": ["मेरीचिपस", "इक्वास", "इओहिप्पस", "मेसोहिप्पस"],
      "a": 2
    },
    {
      "q": "आर्कियोप्टेरिक्स किन दो वर्गों के बीच की योजक कड़ी है?",
      "o": ["जलचर और थलचर", "कीट और पक्षी", "स्तनधारी और जलचर", "सरीसृप तथा पक्षी"],
      "a": 3
    },
    {
      "q": "आनुवंशिक परिवर्तन मुख्य रूप से किस क्रिया में होता है?",
      "o": ["डीएनए प्रतिकृति में", "श्वसन क्रिया में", "पोषण क्रिया में", "उत्सर्जन क्रिया में"],
      "a": 0
    },
    {
      "q": "पादप की ऊँचाई का नियंत्रण किस हार्मोन द्वारा होता है जो जीन पर निर्भर करता है?",
      "o": ["पेप्सिन", "ऑक्सिन", "इंसुलिन", "थायरोक्सिन"],
      "a": 1
    },
    {
      "q": "प्राकृतिक चयन द्वारा जैव विकास की अवधारणा किस पर आधारित है?",
      "o": ["अंगों के उपयोग पर", "उपार्जित लक्षणों पर", "योग्यतम की उत्तरजीविता पर", "अंगों के अनुपयोग पर"],
      "a": 2
    },
    {
      "q": "मानव में एक्स (X) और वाई (Y) गुणसूत्रों को क्या कहते हैं?",
      "o": ["ऑटोसोम", "कायिक गुणसूत्र", "समान गुणसूत्र", "लिंग गुणसूत्र"],
      "a": 3
    },
    {
      "q": "स्त्री में युग्मक (अंडाणु) में कौन सा गुणसूत्र पाया जाता है?",
      "o": ["केवल X गुणसूत्र", "केवल Y गुणसूत्र", "X और Y दोनों", "कोई गुणसूत्र नहीं"],
      "a": 0
    },
    {
      "q": "पुरुष के शुक्राणु में कौन सा गुणसूत्र हो सकता है?",
      "o": ["केवल X गुणसूत्र", "या तो X या Y गुणसूत्र", "केवल Y गुणसूत्र", "कोई नहीं"],
      "a": 1
    },
    {
      "q": "यदि X गुणसूत्र वाला शुक्राणु अंडाणु को निषेचित करे तो संतान क्या होगी?",
      "o": ["लड़का", "जुड़वाँ लड़के", "लड़की", "कोई नहीं"],
      "a": 2
    },
    {
      "q": "यदि Y गुणसूत्र वाला शुक्राणु अंडाणु को निषेचित करे तो संतान क्या होगी?",
      "o": ["लड़की", "जुड़वाँ लड़कियाँ", "कोई नहीं", "लड़का"],
      "a": 3
    },
    {
      "q": "जीन कहाँ स्थित होते हैं?",
      "o": ["गुणसूत्रों पर", "कोशिका भित्ति पर", "हरितलवक पर", "माइटोकॉन्ड्रिया में"],
      "a": 0
    },
    {
      "q": "वंशागत लक्षणों का स्थानांतरण एक पीढ़ी से दूसरी पीढ़ी में किसके द्वारा होता है?",
      "o": ["रक्त द्वारा", "जीन/डीएनए द्वारा", "हार्मोन द्वारा", "भोजन द्वारा"],
      "a": 1
    },
    {
      "q": "पक्षियों और चमगादड़ के पंख का कार्य क्या है?",
      "o": ["तैरना", "दौड़ना", "उड़ना", "पकड़ना"],
      "a": 2
    },
    {
      "q": "जैव विकास को समझाने वाला पहला वैज्ञानिक कौन था?",
      "o": ["डार्विन", "मेंडल", "अरस्तू", "लैमार्क"],
      "a": 3
    },
    {
      "q": "फिलॉसफिक जूलॉजिक पुस्तक के लेखक कौन हैं?",
      "o": ["लैमार्क", "डार्विन", "मेंडल", "पाश्चर"],
      "a": 0
    },
    {
      "q": "किस वैज्ञानिक ने चूहों की पूँछ काटकर प्रयोग किया था?",
      "o": ["डार्विन ने", "वीजमैन ने", "लैमार्क ने", "मेंडल ने"],
      "a": 1
    },
    {
      "q": "वीजमैन के प्रयोग से किस सिद्धांत का खंडन हुआ?",
      "o": ["प्राकृतिक चयन का", "प्रभाविता के नियम का", "उपार्जित लक्षणों की वंशागति का", "स्वतंत्र अपव्यूहन का"],
      "a": 2
    },
    {
      "q": "भौगोलिक पृथक्करण के कारण किस प्रक्रिया में मदद मिलती है?",
      "o": ["पोषण में", "श्वसन में", "उत्सर्जन में", "जाति-उद्भव में"],
      "a": 3
    },
    {
      "q": "अनुवंशिक वाहक किसे माना जाता है?",
      "o": ["गुणसूत्र को", "कोशिका द्रव को", "प्लाज्मा को", "आरबीसी को"],
      "a": 0
    },
    {
      "q": "डीएनए के क्रियात्मक खंड को क्या कहते हैं?",
      "o": ["गुणसूत्र", "जीन", "आरएनए", "प्रोटीन"],
      "a": 1
    },
    {
      "q": "मटर के पौधे का वैज्ञानिक नाम क्या है?",
      "o": ["राणा टिग्रिना", "होमो सेपियंस", "पाइसम सैटाइवम", "मंगल फेरा इंडिका"],
      "a": 2
    },
    {
      "q": "मटर में गोल और झुर्रीदार बीज में कौन सा लक्षण प्रभावी है?",
      "o": ["झुर्रीदार", "लंबा", "बौना", "गोल"],
      "a": 3
    },
    {
      "q": "मटर में पीले और हरे बीज में कौन सा लक्षण प्रभावी है?",
      "o": ["पीला", "हरा", "सफेद", "काला"],
      "a": 0
    },
    {
      "q": "मटर में लंबे और बौने पौधे में कौन सा लक्षण अप्रभावी है?",
      "o": ["लंबा", "बौना", "गोल", "पीला"],
      "a": 1
    },
    {
      "q": "आनुवंशिकता शब्द का प्रयोग सर्वप्रथम किसने किया था?",
      "o": ["मेंडल ने", "जोहान्सन ने", "बैटसन ने", "डार्विन ने"],
      "a": 2
    },
    {
      "q": "डीएनए की दोहरी हेलिक्स संरचना का पता किसने लगाया था?",
      "o": ["मेंडल ने", "डार्विन ने", "लैमार्क ने", "वाटसन और क्रिक ने"],
      "a": 3
    },
    {
      "q": "लैंगिक जनन वाले जीवों में विभिन्नताएँ किस प्रकार उत्पन्न होती हैं?",
      "o": ["क्रॉसिंग ओवर द्वारा", "मुकुलन द्वारा", "द्विखंडन द्वारा", "कायिक प्रवर्धन द्वारा"],
      "a": 0
    },
    {
      "q": "अलैंगिक जनन वाले जीवों में विभिन्नताएँ कैसी होती हैं?",
      "o": ["बहुत अधिक", "बहुत कम", "बिल्कुल नहीं", "असीमित"],
      "a": 1
    },
    {
      "q": "समान आनुवंशिक संरचना वाले जीवों को क्या कहा जाता है?",
      "o": ["संकर", "प्रजाति", "क्लोन", "विभिन्नता"],
      "a": 2
    },
    {
      "q": "मानव में ऑटोसोम की कुल संख्या कितनी होती है?",
      "o": ["23 जोड़े", "46 जोड़े", "2 गुणसूत्र", "22 जोड़े (44 गुणसूत्र)"],
      "a": 3
    },
    {
      "q": "मानव में लिंग गुणसूत्रों के कितने जोड़े होते हैं?",
      "o": ["1 जोड़ा", "22 जोड़े", "23 जोड़े", "2 जोड़े"],
      "a": 0
    },
    {
      "q": "जीन अनुक्रम में अचानक होने वाले परिवर्तन को क्या कहते हैं?",
      "o": ["वंशागति", "उत्परिवर्तन (म्यूटेशन)", "अनुकूलन", "प्रवर्धन"],
      "a": 1
    },
    {
      "q": "मनुष्य के कान की बाहरी कर्णपल्लव की पेशियाँ कैसा अंग हैं?",
      "o": ["समजात अंग", "समवृत्ति अंग", "अवशेषी अंग", "सक्रिय अंग"],
      "a": 2
    },
    {
      "q": "कील और समजात संरचनाओं का अध्ययन किसमें किया जाता है?",
      "o": ["भौतिकी में", "रसायन विज्ञान में", "भूगर्भ विज्ञान में", "तुलनात्मक शरीर रचना विज्ञान में"],
      "a": 3
    },
    {
      "q": "जैव विकास के प्रमाण के रूप में किसे माना जाता है?",
      "o": ["जीवाश्मों को", "पौधों को", "पानी को", "हवा को"],
      "a": 0
    },
    {
      "q": "मेंडल के प्रयोगों में F2 पीढ़ी का अनुपात 3:1 किस क्रॉस में मिला था?",
      "o": ["द्विसंकर क्रॉस में", "एकसंकर क्रॉस में", "त्रिसंकर क्रॉस में", "परीक्षण क्रॉस में"],
      "a": 1
    },
    {
      "q": "डार्विनवाद का मुख्य आधार निम्नलिखित में से क्या है?",
      "o": ["उपार्जित लक्षण", "अंगों का उपयोग", "प्राकृतिक चयन", "उत्परिवर्तन"],
      "a": 2
    },
    {
      "q": "पृथ्वी पर जीवन की उत्पत्ति के समय वायुमंडल में कौन सी गैस स्वतंत्र रूप से नहीं थी?",
      "o": ["नाइट्रोजन", "अमोनिया", "मीथेन", "ऑक्सीजन"],
      "a": 3
    },
    {
      "q": "जीवन की उत्पत्ति के समय प्रारंभिक वायुमंडल में कौन सी गैसें प्रमुख थीं?",
      "o": ["मीथेन अमोनिया और जलवाष्प", "केवल ऑक्सीजन", "केवल कार्बन डाइऑक्साइड", "केवल नाइट्रोजन"],
      "a": 0
    },
    {
      "q": "प्रयोग द्वारा जीवन की उत्पत्ति का विचार किसने प्रमाणित किया था?",
      "o": ["मेंडल ने", "स्टेनली मिलर और उरे ने", "डार्विन ने", "लैमार्क ने"],
      "a": 1
    },
    {
      "q": "स्टेनली मिलर के प्रयोग में किस गैस का उपयोग किया गया था?",
      "o": ["ऑक्सीजन", "ओजोन", "मीथेन और अमोनिया", "क्लोरीन"],
      "a": 2
    },
    {
      "q": "विकासवादी दृष्टिकोण से हमारी किससे अधिक समानता है?",
      "o": ["चीन के विद्यार्थी से", "चिंपैंजी से", "मकड़ी से", "जीवाणु से"],
      "a": 0
    },
    {
      "q": "प्रत्येक कोशिका में डीएनए प्रतिकृति के समय क्या उत्पन्न होती हैं?",
      "o": ["समानताएँ", "विभिन्नताएँ", "बीमारियाँ", "कोशिकाएँ"],
      "a": 1
    },
    {
      "q": "अनुवंशिकता के अध्ययन से संबंधित जीव विज्ञान की शाखा को क्या कहते हैं?",
      "o": ["शरीर क्रिया विज्ञान", "पारिस्थितिकी", "जेनेटिक्स (आनुवंशिकी)", "कोशिका विज्ञान"],
      "a": 2
    },
    {
      "q": "मेंडल ने अपने प्रयोगों को किस संस्था के समक्ष प्रस्तुत किया था?",
      "o": ["रॉयल सोसाइटी", "अकादमी ऑफ साइंस", "विश्व स्वास्थ्य संगठन", "नेचुरल हिस्ट्री सोसाइटी ऑफ ब्रून"],
      "a": 3
    }
  ]
}